LICENSE
MANIFEST.in
README.rst
quik.py
setup.py
docs/source/index.rst
docs/source/team.rst
docs/source/userguide.rst
quik.egg-info/PKG-INFO
quik.egg-info/SOURCES.txt
quik.egg-info/dependency_links.txt
quik.egg-info/not-zip-safe
quik.egg-info/top_level.txt