Metadata-Version: 1.1
Name: quik
Version: 0.2.2
Summary: A fast and lightweight Python template engine
Home-page: https://github.com/avelino/quik
Author: Thiago Avelino
Author-email: thiago@avelino.xxx
License: MIT
Keywords: template,engine,web,fast,lightweight
Platform: UNKNOWN
Classifier: Development Status :: 5 - Production/Stable
Classifier: Environment :: Web Environment
Classifier: Intended Audience :: Developers
Classifier: License :: OSI Approved :: MIT License
Classifier: Operating System :: OS Independent
Classifier: Programming Language :: Python
Classifier: Programming Language :: Python :: 2.6
Classifier: Programming Language :: Python :: 2.7
Classifier: Programming Language :: Python :: 3.3
Classifier: Topic :: Internet :: WWW/HTTP :: Dynamic Content
Classifier: Topic :: Software Development :: Libraries :: Python Modules
Classifier: Topic :: Text Processing :: Markup :: HTML
